libname/CapitalizeFullString.py
libname/__init__.py
capitalizefullsentence-0.1.0.dist-info/METADATA
capitalizefullsentence-0.1.0.dist-info/WHEEL
capitalizefullsentence-0.1.0.dist-info/top_level.txt
capitalizefullsentence-0.1.0.dist-info/RECORD
