Metadata-Version: 2.1
Name: capitalizefullsentence
Version: 0.1.0
Summary: capitalizing full string
Home-page: UNKNOWN
Author: vijay_59 (vijaysinghbhadoriya592@gmail.com)
Author-email: vijaysinghbhadoriya592@gmail.com
License: UNKNOWN
Platform: UNKNOWN
Classifier: Development Status :: 1 - Planning
Classifier: Intended Audience :: Developers
Classifier: Programming Language :: Python :: 3.10
Classifier: Operating System :: Unix
Classifier: Operating System :: MacOS :: MacOS X
Classifier: Operating System :: Microsoft :: Windows
